ptcx/__init__.py
ptcx/__main__.py
ptcx/patch.py
ptcx/utils/fs.py
ptcx/utils/imprt.py
ptcx/utils/langs.py
ptcx/utils/wrap.py
ptcx-0.0.7.dist-info/licenses/LICENSE
ptcx-0.0.7.dist-info/METADATA
ptcx-0.0.7.dist-info/WHEEL
ptcx-0.0.7.dist-info/entry_points.txt
ptcx-0.0.7.dist-info/top_level.txt
ptcx-0.0.7.dist-info/RECORD
